androidviewclient-24.1.0.data/scripts/culebra
androidviewclient-24.1.0.data/scripts/dump
com/__init__.py
com/dtmilano/__init__.py
com/dtmilano/android/__init__.py
com/dtmilano/android/code_generator.py
com/dtmilano/android/common.py
com/dtmilano/android/concertina.py
com/dtmilano/android/controlpanel.py
com/dtmilano/android/culebron.py
com/dtmilano/android/distance.py
com/dtmilano/android/keyevent.py
com/dtmilano/android/plot.py
com/dtmilano/android/viewclient.py
com/dtmilano/android/window.py
com/dtmilano/android/adb/__init__.py
com/dtmilano/android/adb/adbclient.py
com/dtmilano/android/adb/androidkeymap.py
com/dtmilano/android/adb/dumpsys.py
com/dtmilano/android/kato/__init__.py
com/dtmilano/android/kato/kato.py
com/dtmilano/android/robotframework/__init__.py
com/dtmilano/android/robotframework/viewclientwrapper.py
com/dtmilano/android/uiautomator/__init__.py
com/dtmilano/android/uiautomator/uiautomatorhelper.py
com/dtmilano/android/uiautomator/utils.py
share/__init__.py
share/pixmaps/__init__.py
share/pixmaps/culebra.png
share/pixmaps/plugins/__init__.py
share/pixmaps/plugins/android/__init__.py
share/pixmaps/plugins/android/lib/__init__.py
share/pixmaps/plugins/android/lib/device-art-resources/__init__.py
share/pixmaps/plugins/android/lib/device-art-resources/samsung_s4/__init__.py
share/pixmaps/plugins/android/lib/device-art-resources/samsung_s4/port_back.png
share/pixmaps/plugins/android/lib/device-art-resources/samsung_s4/port_fore.png
share/pixmaps/plugins/android/lib/device-art-resources/samsung_s4/port_shadow.png
androidviewclient-24.1.0.dist-info/LICENSE
androidviewclient-24.1.0.dist-info/METADATA
androidviewclient-24.1.0.dist-info/WHEEL
androidviewclient-24.1.0.dist-info/top_level.txt
androidviewclient-24.1.0.dist-info/RECORD
